{
  "items": [
    {
      "brand": "apple",
      "devices": "phone",
      "capacity": "128GB",
      "color": "silver",
      "image": "img/silverPhoneApple.png"
    },
    {
      "brand": "samsung",
      "devices": "laptop",
      "capacity": "512GB",
      "color": "darkBlue",
      "image": "img/blueLaptopSamsung.png"
    },
    {
      "brand": "xiaomi",
      "devices": "tablet",
      "capacity": "256GB",
      "color": "black",
      "image": "img/blackTabletXiaomi.png"
    },
    {
      "brand": "apple",
      "devices": "tablet",
      "capacity": "256GB",
      "color": "darkBlue",
      "image": "img/blueTabletApple.png"
    },
    {
      "brand": "samsung",
      "devices": "phone",
      "capacity": "256GB",
      "color": "silver",
      "image": "img/silverPhoneSamSung.png"
    },
    {
      "brand": "xiaomi",
      "devices": "laptop",
      "capacity": "512GB",
      "color": "black",
      "image": "img/blackLaptopXiaomi.png"
    },
    {
      "brand": "apple",
      "devices": "laptop",
      "capacity": "256GB",
      "color": "silver",
      "image": "img/silverLaptopApple.png"
    },
    {
      "brand": "samsung",
      "devices": "tablet",
      "capacity": "128GB",
      "color": "darkBlue",
      "image": "img/blueTabletSamsung.png"
    },
    {
      "brand": "xiaomi",
      "devices": "phone",
      "capacity": "256GB",
      "color": "black",
      "image": "img/blackPhoneXiaomi.png"
    },
    {
      "brand": "apple",
      "devices": "tablet",
      "capacity": "128GB",
      "color": "darkBlue",
      "image": "img/blueTabletApple.png"
    },
    {
      "brand": "samsung",
      "devices": "laptop",
      "capacity": "512GB",
      "color": "silver",
      "image": "img/silverLaptopSamSung.png"
    },
    {
      "brand": "xiaomi",
      "devices": "tablet",
      "capacity": "128GB",
      "color": "silver",
      "image": "img/silverTabletXiaomi.png"
    },
    {
      "brand": "apple",
      "devices": "phone",
      "capacity": "256GB",
      "color": "black",
      "image": "img/blackPhoneApple.png"
    },
    {
      "brand": "samsung",
      "devices": "phone",
      "capacity": "128GB",
      "color": "darkBlue",
      "image": "img/bluePhoneSamsung.png"
    },
    {
      "brand": "xiaomi",
      "devices": "laptop",
      "capacity": "256GB",
      "color": "silver",
      "image": "img/silverLaptopXiaomi.png"
    },
    {
      "brand": "apple",
      "devices": "laptop",
      "capacity": "128GB",
      "color": "black",
      "image": "img/blackLaptopApple.png"
    },
    {
      "brand": "samsung",
      "devices": "tablet",
      "capacity": "256GB",
      "color": "black",
      "image": "img/blackTabletSamsung.png"
    },
    {
      "brand": "xiaomi",
      "devices": "phone",
      "capacity": "128GB",
      "color": "silver",
      "image": "img/silverPhoneXiaomi.png"
    },
    {
      "brand": "apple",
      "devices": "tablet",
      "capacity": "512GB",
      "color": "silver",
      "image": "img/silverTabletApple.png"
    },
    {
      "brand": "samsung",
      "devices": "laptop",
      "capacity": "256GB",
      "color": "darkBlue",
      "image": "img/blueLaptopSamsung.png"
    }
  ]
}
